package_analyzer.py
pkgaudit.py
python_package_audit-0.1.6.dist-info/licenses/LICENSE
python_package_audit-0.1.6.dist-info/METADATA
python_package_audit-0.1.6.dist-info/WHEEL
python_package_audit-0.1.6.dist-info/top_level.txt
python_package_audit-0.1.6.dist-info/RECORD
