Metadata-Version: 2.4
Name: python-package-audit
Version: 0.1.6
Summary: Python Package Audit is a lightweight static analysis tool designed to detect unused Python packages
Author-email: Omer Menashe <unspecified@mail.com>
License: MIT
Project-URL: Source, https://github.com/iamomerm/python-package-audit
Keywords: python-package-audit,package,audit
Classifier: Programming Language :: Python :: 3
Classifier: License :: OSI Approved :: MIT License
Classifier: Operating System :: OS Independent
Requires-Python: >=3.7
License-File: LICENSE
Requires-Dist: colorama>=0.4.6
Requires-Dist: pipdeptree>=2.27.0
Dynamic: license-file
